huuh_mcp/.env.sample
huuh_mcp/__init__.py
huuh_mcp/callback_server.py
huuh_mcp/instructions.md
huuh_mcp/server.py
huuh_mcp/config/__init__.py
huuh_mcp/config/settings.py
huuh_mcp/huuh/__init__.py
huuh_mcp/huuh/auth.py
huuh_mcp/huuh/client.py
huuh_mcp/tools/__init__.py
huuh_mcp/tools/base.py
huuh_mcp/tools/contribution.py
huuh_mcp/tools/information.py
huuh_mcp/tools/marketplace.py
huuh_mcp/tools/persona.py
huuh_mcp/tools/space.py
huuh_mcp/tools/user_options.py
huuh_mcp/utils/__init__.py
huuh_mcp/utils/auth_wrapper.py
huuh_mcp/utils/logging.py
huuh_mcp-0.2.25.dist-info/METADATA
huuh_mcp-0.2.25.dist-info/WHEEL
huuh_mcp-0.2.25.dist-info/entry_points.txt
huuh_mcp-0.2.25.dist-info/RECORD
