Metadata-Version: 2.4
Name: huuh-mcp
Version: 0.2.25
Summary: collaborative AI
Author-email: Filipp Trigub <filipp.trigub@infolab.ai>
Requires-Python: >=3.12
Requires-Dist: fastmcp>=2.3.4
Requires-Dist: httpx>=0.23.0
Requires-Dist: pydantic-settings>=2.0.0
Requires-Dist: pydantic>=2.11.4
Requires-Dist: python-dotenv>=1.1.0
